cryptonium/__init__.py
cryptonium/utils.py
cryptonium-0.3.0.dist-info/LICENSE.txt
cryptonium-0.3.0.dist-info/WHEEL
cryptonium-0.3.0.dist-info/METADATA
cryptonium-0.3.0.dist-info/RECORD
