Metadata-Version: 2.1
Name: cryptonium
Version: 0.3.0
Summary: Crypto library
Home-page: https://github.com/piper-hq/cryptonium
License: LGPL-3.0+
Keywords: crypto
Author: PiperHQ
Author-email: tech@piperhq.co
Requires-Python: >=3.7.0,<4.0.0
Classifier: Development Status :: 3 - Alpha
Classifier: License :: OSI Approved :: GNU Lesser General Public License v3 or later (LGPLv3+)
Classifier: Operating System :: OS Independent
Classifier: Programming Language :: Python :: 3
Classifier: Programming Language :: Python :: 3.10
Classifier: Programming Language :: Python :: 3.7
Classifier: Programming Language :: Python :: 3.8
Classifier: Programming Language :: Python :: 3.9
Requires-Dist: cryptography (>=36.0.0,<38.0.0)
Project-URL: Repository, https://github.com/piper-hq/cryptonium
